{"username": "baba_baba_whiteman", "userid": "babababawhiteman", "registertime": 1723766400, "group": 1, "ratings": {"gen92v2doubles": {"elo": 1040, "gxe": 55, "rpr": 1540.1606143390134, "rprd": 122.85830807679145, "w": 1, "l": 0, "coil": null}, "gen9anythinggoes": {"elo": 1223.7096020011948, "gxe": 58.8, "rpr": 1567.9289845325725, "rprd": 67.61714344148379, "w": 16, "l": 8, "coil": null}, "gen9doublesou": {"elo": 1150.2054325805307, "gxe": 44.7, "rpr": 1459.4658986386762, "rprd": 70.96039534166778, "w": 15, "l": 14, "coil": null}, "gen9doublesubers": {"elo": 1000, "gxe": 35, "rpr": 1382.7562423762959, "rprd": 46.10181392064872, "w": 33, "l": 57, "coil": null}, "gen9randombattle": {"elo": 1346.7929876763492, "gxe": 55.2, "rpr": 1539.5776580754573, "rprd": 36.38232895019782, "w": 357, "l": 369, "coil": null}, "gen9randomdoublesbattle": {"elo": 1025.405468249908, "gxe": 31.9, "rpr": 1351.4963220032944, "rprd": 96.71847324970318, "w": 3, "l": 9, "coil": null}, "gen9ubers": {"elo": 1122.9247766636547, "gxe": 39.8, "rpr": 1417.3185288099412, "rprd": 121.08046571795413, "w": 26, "l": 25, "coil": null}}}