{"username": "etetete", "userid": "etetete", "registertime": 1446940800, "group": 1, "ratings": {"gen3ou": {"elo": 1083.2667139366, "gxe": 58.6, "rpr": 1569.0750162463, "rprd": 116.13904455327, "w": 0, "l": 0, "coil": null}, "gen6randombattle": {"elo": 1040, "gxe": 55, "rpr": 1540.1606143388, "rprd": 122.8583080769, "w": 0, "l": 0, "coil": null}, "gen7hackmonscup": {"elo": 1000, "gxe": 45.3, "rpr": 1462.5670239272, "rprd": 121.968632345, "w": 0, "l": 0, "coil": null}, "gen7randombattle": {"elo": 1499.4646151853, "gxe": 80.4, "rpr": 1816.8591008392, "rprd": 221.3687186326, "w": 9422, "l": 8839, "coil": null}, "gen7randomdoublesbattle": {"elo": 1000, "gxe": 46.5, "rpr": 1472.1706968404, "rprd": 122.95951610181, "w": 0, "l": 0, "coil": null}, "gen8randombattle": {"elo": 1399.5204928852, "gxe": 77.7, "rpr": 1775.8580903862, "rprd": 210.10450758989, "w": 7098, "l": 6329, "coil": null}, "gen8randombattleblitz": {"elo": 1331.7883872402, "gxe": 68.5, "rpr": 1648.8069121078, "rprd": 65.184674692928, "w": 18, "l": 6, "coil": null}, "gen9randombattle": {"elo": 1954.0879526602691, "gxe": 82.8, "rpr": 1795.6720133708154, "rprd": 26.704595467262415, "w": 10640, "l": 10130, "coil": null}, "gen9randombattleblitz": {"elo": 1664.0558737275708, "gxe": 71.1, "rpr": 1671.146757564717, "rprd": 54.27769148530513, "w": 306, "l": 240, "coil": null}, "randomdoublesbattle": {"elo": 1031.2291760085, "gxe": 50.6, "rpr": 1504.6477618805, "rprd": 116.05019062802, "w": 0, "l": 0, "coil": null}}}