{"username": "hectorleon", "userid": "hectorleon", "registertime": 0, "group": 0, "ratings": {"battlespotsingles": {"elo": 1000, "gxe": 32.9, "rpr": 1361.0179536639, "rprd": 96.037926599326, "w": 1, "l": 6, "coil": null}, "gen1randombattle": {"elo": 1000, "gxe": 38.2, "rpr": 1403.5706429349, "rprd": 130, "w": 0, "l": 2, "coil": null}, "gen6battlefactory": {"elo": 1000, "gxe": 45, "rpr": 1459.8393856612, "rprd": 122.8583080769, "w": 0, "l": 1, "coil": null}, "gen6randombattle": {"elo": 1000, "gxe": 45, "rpr": 1459.8393856612, "rprd": 122.8583080769, "w": 0, "l": 1, "coil": null}, "gen7battlefactory": {"elo": 1063.0557167206, "gxe": 57, "rpr": 1556.0913090831, "rprd": 122.71123106827, "w": 1, "l": 0, "coil": null}, "gen7bssfactory": {"elo": 1052.236101697, "gxe": 53.2, "rpr": 1525.6153394423, "rprd": 123.24643863238, "w": 1, "l": 0, "coil": null}, "gen7randombattle": {"elo": 1261.426836754, "gxe": 39.5, "rpr": 1419.5822764084, "rprd": 25, "w": 721, "l": 923, "coil": null}, "gen7randomdoublesbattle": {"elo": 1000, "gxe": 45.2, "rpr": 1461.8461505682, "rprd": 122.16817523523, "w": 0, "l": 1, "coil": null}, "gen7superstaffbrosbrawl": {"elo": 1000, "gxe": 45, "rpr": 1459.8393856612, "rprd": 122.8583080769, "w": 0, "l": 1, "coil": null}, "gen8randombattle": {"elo": 1154.5213215885, "gxe": 42.4, "rpr": 1442.6006694151, "rprd": 25, "w": 3442, "l": 4344, "coil": null}, "gen8randomdoublesbattle": {"elo": 1063.2034424101, "gxe": 51, "rpr": 1507.8634420815, "rprd": 112.2624738134, "w": 2, "l": 1, "coil": null}, "gen9randombattle": {"elo": 1105.222593113156, "gxe": 41.4, "rpr": 1434.2801703026828, "rprd": 48.55946116960939, "w": 2250, "l": 2806, "coil": null}, "gen9randombattleblitz": {"elo": 1000, "gxe": 44.7, "rpr": 1457.4034532168446, "rprd": 122.88213741425159, "w": 0, "l": 1, "coil": null}, "gen9randomdoublesbattle": {"elo": 1046.6260158619723, "gxe": 54.9, "rpr": 1539.231010019495, "rprd": 122.24438654660149, "w": 1, "l": 0, "coil": null}}}