{"username": "kianlegoat", "userid": "kianlegoat", "registertime": 1779235200, "group": 1, "ratings": {"gen9ou": {"elo": 1104.2006237946744, "gxe": 53.4, "rpr": 1526.7338596839181, "rprd": 90.39251493542949, "w": 6, "l": 3, "coil": null}, "gen9randombattle": {"elo": 1327.4575165541987, "gxe": 56.7, "rpr": 1550.6202392771293, "rprd": 35.65044326397881, "w": 99, "l": 88, "coil": null}, "gen9randomdoublesbattle": {"elo": 1144.833335347347, "gxe": 54, "rpr": 1530.5339074627325, "rprd": 55.29975894888697, "w": 24, "l": 19, "coil": null}}}