{"username": "SenpaiCry", "userid": "senpaicry", "registertime": 1408665600, "group": 1, "ratings": {"anythinggoes": {"elo": 1000, "gxe": 45, "rpr": 1459.8393856612, "rprd": 122.8583080769, "w": 0, "l": 1, "coil": null}, "gen1randombattle": {"elo": 1052.3386899519, "gxe": 51.4, "rpr": 1510.9463281707, "rprd": 114.60654089176, "w": 2, "l": 2, "coil": null}, "gen5randombattle": {"elo": 1016.0981579007714, "gxe": 43.6, "rpr": 1449.0208560211188, "rprd": 121.85363012623802, "w": 1, "l": 2, "coil": null}, "gen6randombattle": {"elo": 1182.2162171568252, "gxe": 67.7, "rpr": 1646.0869082960935, "rprd": 110.71463067615923, "w": 6, "l": 1, "coil": null}, "gen7ou": {"elo": 1077.9351370016, "gxe": 34.9, "rpr": 1378.2783176222, "rprd": 97.830315125223, "w": 8, "l": 11, "coil": null}, "gen7randombattle": {"elo": 1295.6688336283191, "gxe": 65, "rpr": 1620.2707718434135, "rprd": 87.44868150438532, "w": 26, "l": 16, "coil": null}, "gen8ou": {"elo": 1028.8559843386, "gxe": 31.1, "rpr": 1347.1094402892, "rprd": 74.784338176363, "w": 10, "l": 24, "coil": null}, "gen8pu": {"elo": 1000, "gxe": 45, "rpr": 1459.8393856612, "rprd": 122.8583080769, "w": 0, "l": 1, "coil": null}, "gen8randombattle": {"elo": 1410.1419651347, "gxe": 63.4, "rpr": 1618.60672087, "rprd": 191.65827148972, "w": 560, "l": 512, "coil": null}, "gen9championsrandombattle": {"elo": 1048.9835058430779, "gxe": 50.4, "rpr": 1503.1698302166008, "rprd": 116.2822967640428, "w": 1, "l": 1, "coil": null}, "gen9ou": {"elo": 1053.3620220432701, "gxe": 31, "rpr": 1346.2361350797228, "rprd": 77.63120731355767, "w": 7, "l": 12, "coil": null}, "gen9randombattle": {"elo": 1546.0212692297537, "gxe": 63.7, "rpr": 1606.2806858463857, "rprd": 40.58427579845013, "w": 688, "l": 662, "coil": null}, "gen9randombattleblitz": {"elo": 1042.5613222537736, "gxe": 39, "rpr": 1411.78191514584, "rprd": 112.58528242999147, "w": 1, "l": 3, "coil": null}, "gen9randomdoublesbattle": {"elo": 1000, "gxe": 44.2, "rpr": 1453.3493171104042, "rprd": 122.71413600432325, "w": 0, "l": 1, "coil": null}, "gen9uu": {"elo": 1112.744485396894, "gxe": 56.2, "rpr": 1548.9637968410273, "rprd": 106.61860779553166, "w": 4, "l": 2, "coil": null}, "godsandfollowers": {"elo": 1030.7425664237, "gxe": 48.1, "rpr": 1485.1949446959, "rprd": 99.670957431182, "w": 3, "l": 3, "coil": null}, "ru": {"elo": 1035.8062818114, "gxe": 31.3, "rpr": 1348.3350416868, "rprd": 82.605787167392, "w": 2, "l": 10, "coil": null}, "seasonalpolaropposites": {"elo": 1000, "gxe": 47, "rpr": 1476.1554167329, "rprd": 123.43629968098, "w": 0, "l": 1, "coil": null}, "seasonalsuperstaffbrosmelee": {"elo": 1007.0261844786, "gxe": 42.7, "rpr": 1442.0537706042, "rprd": 105.90581101621, "w": 1, "l": 3, "coil": null}, "ubers": {"elo": 1000, "gxe": 31.5, "rpr": 1347.3625676569, "rprd": 102.47623814758, "w": 0, "l": 5, "coil": null}}}