{"id": "gen9randombattle-2642215643", "format": "[Gen 9] Random Battle", "players": ["baraoforesta", "matheuskiller"], "log": "|j|\u2606baraoforesta\n|j|\u2606matheuskiller\n|t:|1782912139\n|gametype|singles\n|player|p1|baraoforesta|skyla|\n|player|p2|matheuskiller|cynthia|\n|gen|9\n|tier|[Gen 9] Random Battle\n|rule|Species Clause: Limit one of each Pok\u00e9mon\n|rule|HP Percentage Mod: HP is shown in percentages\n|rule|Sleep Clause Mod: Limit one foe put to sleep\n|rule|Illusion Level Mod: Illusion disguises the Pok\u00e9mon's true level\n|\n|t:|1782912139\n|teamsize|p1|6\n|teamsize|p2|6\n|start\n|switch|p1a: Regirock|Regirock, L83|268/268\n|switch|p2a: Dondozo|Dondozo, L78, M|362/362\n|turn|1\n|inactive|Battle timer is ON: inactive players will automatically lose when time's up. (requested by matheuskiller)\n|\n|t:|1782912147\n|move|p1a: Regirock|Thunder Wave|p2a: Dondozo\n|-status|p2a: Dondozo|par\n|cant|p2a: Dondozo|par\n|\n|upkeep\n|turn|2\n|\n|t:|1782912152\n|move|p1a: Regirock|Stealth Rock|p2a: Dondozo\n|-sidestart|p2: matheuskiller|move: Stealth Rock\n|move|p2a: Dondozo|Curse|p2a: Dondozo\n|-unboost|p2a: Dondozo|spe|1\n|-boost|p2a: Dondozo|atk|1\n|-boost|p2a: Dondozo|def|1\n|\n|upkeep\n|turn|3\n|\n|t:|1782912163\n|move|p1a: Regirock|Body Press|p2a: Dondozo\n|-damage|p2a: Dondozo|307/362 par\n|cant|p2a: Dondozo|par\n|\n|-heal|p2a: Dondozo|329/362 par|[from] item: Leftovers\n|upkeep\n|turn|4\n|\n|t:|1782912182\n|switch|p1a: Drifblim|Drifblim, L86, F|396/396\n|cant|p2a: Dondozo|par\n|\n|-heal|p2a: Dondozo|351/362 par|[from] item: Leftovers\n|upkeep\n|turn|5\n|\n|t:|1782912189\n|move|p1a: Drifblim|Calm Mind|p1a: Drifblim\n|-boost|p1a: Drifblim|spa|1\n|-boost|p1a: Drifblim|spd|1\n|move|p2a: Dondozo|Curse|p2a: Dondozo\n|-unboost|p2a: Dondozo|spe|1\n|-boost|p2a: Dondozo|atk|1\n|-boost|p2a: Dondozo|def|1\n|\n|-heal|p2a: Dondozo|362/362 par|[from] item: Leftovers\n|upkeep\n|turn|6\n|\n|t:|1782912198\n|move|p1a: Drifblim|Calm Mind|p1a: Drifblim\n|-boost|p1a: Drifblim|spa|1\n|-boost|p1a: Drifblim|spd|1\n|move|p2a: Dondozo|Wave Crash|p1a: Drifblim\n|-damage|p1a: Drifblim|44/396\n|-enditem|p1a: Drifblim|Sitrus Berry|[eat]\n|-heal|p1a: Drifblim|143/396|[from] item: Sitrus Berry\n|-damage|p2a: Dondozo|246/362 par|[from] Recoil\n|\n|-heal|p2a: Dondozo|268/362 par|[from] item: Leftovers\n|upkeep\n|turn|7\n|\n|t:|1782912204\n|move|p1a: Drifblim|Strength Sap|p2a: Dondozo\n|-unboost|p2a: Dondozo|atk|1\n|-heal|p1a: Drifblim|396/396\n|move|p2a: Dondozo|Wave Crash|p1a: Drifblim\n|-damage|p1a: Drifblim|132/396\n|-damage|p2a: Dondozo|181/362 par|[from] Recoil\n|\n|-heal|p2a: Dondozo|203/362 par|[from] item: Leftovers\n|upkeep\n|turn|8\n|\n|t:|1782912210\n|move|p1a: Drifblim|Strength Sap|p2a: Dondozo\n|-unboost|p2a: Dondozo|atk|1\n|-heal|p1a: Drifblim|396/396\n|cant|p2a: Dondozo|par\n|\n|-heal|p2a: Dondozo|225/362 par|[from] item: Leftovers\n|upkeep\n|turn|9\n|\n|t:|1782912217\n|move|p1a: Drifblim|Air Slash|p2a: Dondozo\n|-damage|p2a: Dondozo|125/362 par\n|move|p2a: Dondozo|Wave Crash|p1a: Drifblim\n|-damage|p1a: Drifblim|225/396\n|-damage|p2a: Dondozo|69/362 par|[from] Recoil\n|\n|-heal|p2a: Dondozo|91/362 par|[from] item: Leftovers\n|upkeep\n|turn|10\n|\n|t:|1782912222\n|move|p1a: Drifblim|Strength Sap|p2a: Dondozo\n|-unboost|p2a: Dondozo|atk|1\n|-heal|p1a: Drifblim|396/396\n|move|p2a: Dondozo|Wave Crash|p1a: Drifblim\n|-damage|p1a: Drifblim|285/396\n|-damage|p2a: Dondozo|54/362 par|[from] Recoil\n|\n|-heal|p2a: Dondozo|76/362 par|[from] item: Leftovers\n|upkeep\n|turn|11\n|\n|t:|1782912234\n|move|p1a: Drifblim|Air Slash|p2a: Dondozo\n|-damage|p2a: Dondozo|0 fnt\n|faint|p2a: Dondozo\n|\n|upkeep\n|\n|t:|1782912244\n|switch|p2a: Roaring Moon|Roaring Moon, L72|270/270\n|-damage|p2a: Roaring Moon|237/270|[from] Stealth Rock\n|turn|12\n|\n|t:|1782912252\n|move|p1a: Drifblim|Air Slash|p2a: Roaring Moon\n|-damage|p2a: Roaring Moon|86/270\n|move|p2a: Roaring Moon|Dragon Dance|p2a: Roaring Moon\n|-boost|p2a: Roaring Moon|atk|1\n|-boost|p2a: Roaring Moon|spe|1\n|\n|upkeep\n|turn|13\n|\n|t:|1782912259\n|move|p1a: Drifblim|Air Slash|p2a: Roaring Moon\n|-damage|p2a: Roaring Moon|0 fnt\n|faint|p2a: Roaring Moon\n|-end|p2a: Roaring Moon|Protosynthesis|[silent]\n|\n|upkeep\n|\n|t:|1782912272\n|switch|p2a: Azelf|Azelf, L82|257/257\n|-damage|p2a: Azelf|225/257|[from] Stealth Rock\n|turn|14\n|\n|t:|1782912276\n|move|p1a: Drifblim|Shadow Ball|p2a: Azelf\n|-supereffective|p2a: Azelf\n|-damage|p2a: Azelf|0 fnt\n|faint|p2a: Azelf\n|\n|upkeep\n|\n|t:|1782912284\n|switch|p2a: Vaporeon|Vaporeon, L86, M|364/364\n|-damage|p2a: Vaporeon|319/364|[from] Stealth Rock\n|turn|15\n|\n|t:|1782912292\n|move|p1a: Drifblim|Calm Mind|p1a: Drifblim\n|-boost|p1a: Drifblim|spa|1\n|-boost|p1a: Drifblim|spd|1\n|move|p2a: Vaporeon|Scald|p1a: Drifblim\n|-damage|p1a: Drifblim|227/396\n|\n|-heal|p2a: Vaporeon|341/364|[from] item: Leftovers\n|upkeep\n|turn|16\n|\n|t:|1782912300\n|move|p1a: Drifblim|Air Slash|p2a: Vaporeon\n|-damage|p2a: Vaporeon|173/364\n|move|p2a: Vaporeon|Scald|p1a: Drifblim\n|-damage|p1a: Drifblim|176/396\n|\n|-heal|p2a: Vaporeon|195/364|[from] item: Leftovers\n|upkeep\n|turn|17\n|\n|t:|1782912313\n|move|p1a: Drifblim|Shadow Ball|p2a: Vaporeon\n|-damage|p2a: Vaporeon|0 fnt\n|faint|p2a: Vaporeon\n|\n|upkeep\n|\n|t:|1782912316\n|switch|p2a: Venusaur|Venusaur, L84, F|272/272\n|-damage|p2a: Venusaur|238/272|[from] Stealth Rock\n|turn|18\n|\n|t:|1782912320\n|move|p1a: Drifblim|Air Slash|p2a: Venusaur\n|-supereffective|p2a: Venusaur\n|-damage|p2a: Venusaur|0 fnt\n|faint|p2a: Venusaur\n|\n|upkeep\n|\n|t:|1782912322\n|switch|p2a: Okidogi|Okidogi, L77, M|262/262\n|-damage|p2a: Okidogi|246/262|[from] Stealth Rock\n|turn|19\n|\n|t:|1782912327\n|move|p1a: Drifblim|Air Slash|p2a: Okidogi\n|-supereffective|p2a: Okidogi\n|-damage|p2a: Okidogi|0 fnt\n|faint|p2a: Okidogi\n|\n|win|baraoforesta\n|l|\u2606matheuskiller\n|player|p2|\n", "inputlog": ">version f8ac14003a5f27e1bdc8d8c59608a773c1cb96e5\n>start {\"formatid\":\"gen9randombattle\",\"seed\":\"sodium,0a725824865aeb68af590771cfc226a4\"}\n>player p1 {\"name\":\"baraoforesta\",\"avatar\":\"skyla\",\"rating\":0,\"seed\":\"sodium,039eaff0b4a082592c36368a6c8883b9\"}\n>player p2 {\"name\":\"matheuskiller\",\"avatar\":\"cynthia\",\"rating\":0,\"seed\":\"sodium,53f616a770e6e0991c5ddc0783d55af8\"}\n>p1 move thunderwave\n>p2 move curse\n>p1 move stealthrock\n>p2 move curse\n>p1 move bodypress\n>p2 move curse\n>p1 switch 6\n>p2 move curse\n>p1 move calmmind\n>p2 move curse\n>p1 move calmmind\n>p2 move wavecrash\n>p1 move strengthsap\n>p2 move wavecrash\n>p1 move strengthsap\n>p2 move wavecrash\n>p1 move airslash\n>p2 move wavecrash\n>p1 move strengthsap\n>p2 move wavecrash\n>p1 move airslash\n>p2 move wavecrash\n>p2 switch 3\n>p1 move airslash\n>p2 move dragondance\n>p1 move airslash\n>p2 move knockoff\n>p2 switch 6\n>p1 move shadowball\n>p2 move fireblast\n>p2 switch 2\n>p1 move calmmind\n>p2 move scald\n>p1 move airslash\n>p2 move scald\n>p1 move shadowball\n>p2 move scald\n>p2 switch 5\n>p1 move airslash\n>p2 move leechseed\n>p2 switch 4\n>p1 move airslash\n>p2 move knockoff", "uploadtime": 1782912334, "views": 9, "formatid": "gen9randombattle", "rating": null, "private": 0, "password": null, "player_dets": [{"name": "baraoforesta", "avatar": "skyla", "rating": 0, "seed": "sodium,039eaff0b4a082592c36368a6c8883b9"}, {"name": "matheuskiller", "avatar": "cynthia", "rating": 0, "seed": "sodium,53f616a770e6e0991c5ddc0783d55af8"}], "teams_full": [{"Regirock": {"name": "Regirock", "species": "Regirock", "speciesId": "regirock", "gender": "N", "shiny": false, "level": 83, "moves": ["bodypress", "stealthrock", "stoneedge", "thunderwave"], "ability": "Clear Body", "evs": {"hp": 85, "atk": 85, "def": 85, "spa": 85, "spd": 85, "spe": 85}, "ivs": {"hp": 31, "atk": 31, "def": 31, "spa": 31, "spd": 31, "spe": 31}, "item": "Leftovers", "teraType": "Fighting", "role": "Bulky Attacker", "bvs": {"hp": 80, "atk": 100, "def": 200, "spa": 50, "spd": 100, "spe": 50}, "stats": {"hp": 268, "atk": 214, "def": 380, "spa": 131, "spd": 214, "spe": 131}, "types": ["Rock"]}, "Vivillon": {"name": "Vivillon", "species": "Vivillon-Polar", "speciesId": "vivillon", "gender": "M", "shiny": false, "level": 83, "moves": ["quiverdance", "hurricane", "terablast", "sleeppowder"], "ability": "Compound Eyes", "evs": {"hp": 85, "atk": 0, "def": 85, "spa": 85, "spd": 85, "spe": 85}, "ivs": {"hp": 31, "atk": 0, "def": 31, "spa": 31, "spd": 31, "spe": 31}, "item": "Heavy-Duty Boots", "teraType": "Ground", "role": "Tera Blast user", "bvs": {"hp": 80, "atk": 52, "def": 50, "spa": 90, "spd": 50, "spe": 89}, "stats": {"hp": 268, "atk": 91, "def": 131, "spa": 197, "spd": 131, "spe": 195}, "types": ["Bug", "Flying"]}, "Mewtwo": {"name": "Mewtwo", "species": "Mewtwo", "speciesId": "mewtwo", "gender": "N", "shiny": false, "level": 72, "moves": ["psystrike", "nastyplot", "darkpulse", "aurasphere"], "ability": "Pressure", "evs": {"hp": 85, "atk": 0, "def": 85, "spa": 85, "spd": 85, "spe": 85}, "ivs": {"hp": 31, "atk": 0, "def": 31, "spa": 31, "spd": 31, "spe": 31}, "item": "Life Orb", "teraType": "Dark", "role": "Setup Sweeper", "bvs": {"hp": 106, "atk": 110, "def": 90, "spa": 154, "spd": 90, "spe": 130}, "stats": {"hp": 272, "atk": 163, "def": 172, "spa": 264, "spd": 172, "spe": 229}, "types": ["Psychic"]}, "Archaludon": {"name": "Archaludon", "species": "Archaludon", "speciesId": "archaludon", "gender": "M", "shiny": false, "level": 78, "moves": ["dracometeor", "thunderwave", "bodypress", "flashcannon"], "ability": "Stamina", "evs": {"hp": 85, "atk": 0, "def": 85, "spa": 85, "spd": 85, "spe": 85}, "ivs": {"hp": 31, "atk": 0, "def": 31, "spa": 31, "spd": 31, "spe": 31}, "item": "Leftovers", "teraType": "Fighting", "role": "Bulky Attacker", "bvs": {"hp": 90, "atk": 105, "def": 130, "spa": 125, "spd": 65, "spe": 85}, "stats": {"hp": 268, "atk": 168, "def": 248, "spa": 240, "spd": 146, "spe": 178}, "types": ["Steel", "Dragon"]}, "Crawdaunt": {"name": "Crawdaunt", "species": "Crawdaunt", "speciesId": "crawdaunt", "gender": "M", "shiny": false, "level": 84, "moves": ["knockoff", "crabhammer", "dragondance", "closecombat"], "ability": "Adaptability", "evs": {"hp": 85, "atk": 85, "def": 85, "spa": 85, "spd": 85, "spe": 85}, "ivs": {"hp": 31, "atk": 31, "def": 31, "spa": 31, "spd": 31, "spe": 31}, "item": "Life Orb", "teraType": "Fighting", "role": "Fast Attacker", "bvs": {"hp": 63, "atk": 120, "def": 85, "spa": 90, "spd": 55, "spe": 55}, "stats": {"hp": 243, "atk": 250, "def": 191, "spa": 199, "spd": 141, "spe": 141}, "types": ["Water", "Dark"]}, "Drifblim": {"name": "Drifblim", "species": "Drifblim", "speciesId": "drifblim", "gender": "F", "shiny": false, "level": 86, "moves": ["strengthsap", "airslash", "calmmind", "shadowball"], "ability": "Unburden", "evs": {"hp": 73, "atk": 0, "def": 85, "spa": 85, "spd": 85, "spe": 85}, "ivs": {"hp": 31, "atk": 0, "def": 31, "spa": 31, "spd": 31, "spe": 31}, "item": "Sitrus Berry", "teraType": "Steel", "role": "Bulky Attacker", "bvs": {"hp": 150, "atk": 80, "def": 44, "spa": 90, "spd": 54, "spe": 80}, "stats": {"hp": 396, "atk": 142, "def": 125, "spa": 204, "spd": 142, "spe": 187}, "types": ["Ghost", "Flying"]}}, {"Dondozo": {"name": "Dondozo", "species": "Dondozo", "speciesId": "dondozo", "gender": "M", "shiny": false, "level": 78, "moves": ["rest", "wavecrash", "curse", "sleeptalk"], "ability": "Unaware", "evs": {"hp": 85, "atk": 85, "def": 85, "spa": 85, "spd": 85, "spe": 85}, "ivs": {"hp": 31, "atk": 31, "def": 31, "spa": 31, "spd": 31, "spe": 31}, "item": "Leftovers", "teraType": "Dragon", "role": "Bulky Setup", "bvs": {"hp": 150, "atk": 100, "def": 115, "spa": 65, "spd": 65, "spe": 35}, "stats": {"hp": 362, "atk": 201, "def": 224, "spa": 146, "spd": 146, "spe": 100}, "types": ["Water"]}, "Vaporeon": {"name": "Vaporeon", "species": "Vaporeon", "speciesId": "vaporeon", "gender": "M", "shiny": false, "level": 86, "moves": ["flipturn", "wish", "scald", "protect"], "ability": "Water Absorb", "evs": {"hp": 85, "atk": 85, "def": 85, "spa": 85, "spd": 85, "spe": 85}, "ivs": {"hp": 31, "atk": 31, "def": 31, "spa": 31, "spd": 31, "spe": 31}, "item": "Leftovers", "teraType": "Poison", "role": "Bulky Support", "bvs": {"hp": 130, "atk": 65, "def": 60, "spa": 110, "spd": 95, "spe": 65}, "stats": {"hp": 364, "atk": 161, "def": 152, "spa": 238, "spd": 213, "spe": 161}, "types": ["Water"]}, "Roaring Moon": {"name": "Roaring Moon", "species": "Roaring Moon", "speciesId": "roaringmoon", "gender": "N", "shiny": false, "level": 72, "moves": ["knockoff", "roost", "outrage", "dragondance"], "ability": "Protosynthesis", "evs": {"hp": 85, "atk": 85, "def": 85, "spa": 85, "spd": 85, "spe": 85}, "ivs": {"hp": 31, "atk": 31, "def": 31, "spa": 31, "spd": 31, "spe": 31}, "item": "Lum Berry", "teraType": "Dark", "role": "Setup Sweeper", "bvs": {"hp": 105, "atk": 139, "def": 71, "spa": 55, "spd": 101, "spe": 119}, "stats": {"hp": 270, "atk": 242, "def": 144, "spa": 121, "spd": 187, "spe": 213}, "types": ["Dragon", "Dark"]}, "Okidogi": {"name": "Okidogi", "species": "Okidogi", "speciesId": "okidogi", "gender": "M", "shiny": false, "level": 77, "moves": ["knockoff", "gunkshot", "bulkup", "drainpunch"], "ability": "Toxic Chain", "evs": {"hp": 85, "atk": 85, "def": 85, "spa": 85, "spd": 85, "spe": 85}, "ivs": {"hp": 31, "atk": 31, "def": 31, "spa": 31, "spd": 31, "spe": 31}, "item": "Leftovers", "teraType": "Dark", "role": "Bulky Setup", "bvs": {"hp": 88, "atk": 128, "def": 115, "spa": 58, "spd": 86, "spe": 80}, "stats": {"hp": 262, "atk": 242, "def": 222, "spa": 134, "spd": 177, "spe": 168}, "types": ["Poison", "Fighting"]}, "Venusaur": {"name": "Venusaur", "species": "Venusaur", "speciesId": "venusaur", "gender": "F", "shiny": false, "level": 84, "moves": ["sludgebomb", "substitute", "sleeppowder", "leechseed"], "ability": "Chlorophyll", "evs": {"hp": 85, "atk": 0, "def": 85, "spa": 85, "spd": 85, "spe": 85}, "ivs": {"hp": 31, "atk": 0, "def": 31, "spa": 31, "spd": 31, "spe": 31}, "item": "Leftovers", "teraType": "Water", "role": "Bulky Support", "bvs": {"hp": 80, "atk": 82, "def": 83, "spa": 100, "spd": 100, "spe": 80}, "stats": {"hp": 272, "atk": 142, "def": 188, "spa": 216, "spd": 216, "spe": 183}, "types": ["Grass", "Poison"]}, "Azelf": {"name": "Azelf", "species": "Azelf", "speciesId": "azelf", "gender": "N", "shiny": false, "level": 82, "moves": ["nastyplot", "fireblast", "dazzlinggleam", "psyshock"], "ability": "Levitate", "evs": {"hp": 85, "atk": 0, "def": 85, "spa": 85, "spd": 85, "spe": 85}, "ivs": {"hp": 31, "atk": 0, "def": 31, "spa": 31, "spd": 31, "spe": 31}, "item": "Life Orb", "teraType": "Fire", "role": "Fast Attacker", "bvs": {"hp": 75, "atk": 125, "def": 70, "spa": 125, "spd": 70, "spe": 115}, "stats": {"hp": 257, "atk": 210, "def": 162, "spa": 252, "spd": 162, "spe": 236}, "types": ["Psychic"]}}]}