{"id": "gen9randombattle-2631900309", "format": "[Gen 9] Random Battle", "players": ["wazzzhole", "imjustabanana"], "log": "|j|\u2606wazzzhole\n|j|\u2606imjustabanana\n|t:|1781453582\n|gametype|singles\n|player|p1|wazzzhole|266|1698\n|player|p2|imjustabanana|giovanni|1707\n|gen|9\n|tier|[Gen 9] Random Battle\n|rated|\n|rule|Species Clause: Limit one of each Pok\u00e9mon\n|rule|HP Percentage Mod: HP is shown in percentages\n|rule|Sleep Clause Mod: Limit one foe put to sleep\n|rule|Illusion Level Mod: Illusion disguises the Pok\u00e9mon's true level\n|\n|t:|1781453582\n|teamsize|p1|6\n|teamsize|p2|6\n|start\n|switch|p1a: Sunflora|Sunflora, M|312/312\n|switch|p2a: Iron Valiant|Iron Valiant, L78|244/244\n|turn|1\n|inactive|Battle timer is ON: inactive players will automatically lose when time's up. (requested by wazzzhole)\n|\n|t:|1781453594\n|move|p2a: Iron Valiant|Calm Mind|p2a: Iron Valiant\n|-boost|p2a: Iron Valiant|spa|1\n|-boost|p2a: Iron Valiant|spd|1\n|move|p1a: Sunflora|Sunny Day|p1a: Sunflora\n|-weather|SunnyDay\n|\n|-weather|SunnyDay|[upkeep]\n|upkeep\n|turn|2\n|\n|t:|1781453609\n|-terastallize|p1a: Sunflora|Fire\n|move|p1a: Sunflora|Weather Ball|p2a: Iron Valiant\n|-damage|p2a: Iron Valiant|0 fnt\n|faint|p2a: Iron Valiant\n|-end|p2a: Iron Valiant|Quark Drive|[silent]\n|-damage|p1a: Sunflora|281/312|[from] item: Life Orb\n|\n|-weather|SunnyDay|[upkeep]\n|upkeep\n|\n|t:|1781453633\n|switch|p2a: Venusaur|Venusaur, L84, M|272/272\n|turn|3\n|\n|t:|1781453636\n|move|p2a: Venusaur|Earth Power|p1a: Sunflora\n|-supereffective|p1a: Sunflora\n|-damage|p1a: Sunflora|173/312\n|move|p1a: Sunflora|Weather Ball|p2a: Venusaur\n|-supereffective|p2a: Venusaur\n|-damage|p2a: Venusaur|0 fnt\n|faint|p2a: Venusaur\n|-damage|p1a: Sunflora|142/312|[from] item: Life Orb\n|\n|-weather|SunnyDay|[upkeep]\n|upkeep\n|\n|t:|1781453646\n|switch|p2a: Klefki|Klefki, L84, F|233/233\n|turn|4\n|\n|t:|1781453651\n|move|p2a: Klefki|Spikes|p1a: Sunflora\n|-sidestart|p1: wazzzhole|Spikes\n|move|p1a: Sunflora|Weather Ball|p2a: Klefki\n|-supereffective|p2a: Klefki\n|-damage|p2a: Klefki|0 fnt\n|faint|p2a: Klefki\n|-damage|p1a: Sunflora|111/312|[from] item: Life Orb\n|\n|-weather|SunnyDay|[upkeep]\n|upkeep\n|\n|t:|1781453653\n|switch|p2a: Zangoose|Zangoose, L85, M|263/263\n|turn|5\n|\n|t:|1781453670\n|switch|p1a: Dialga|Dialga, L73|266/266\n|-damage|p1a: Dialga|233/266|[from] Spikes\n|-ability|p1a: Dialga|Pressure\n|move|p2a: Zangoose|Quick Attack|p1a: Dialga\n|-resisted|p1a: Dialga\n|-damage|p1a: Dialga|209/266\n|\n|-weather|none\n|-heal|p1a: Dialga|225/266|[from] item: Leftovers\n|-status|p2a: Zangoose|tox|[from] item: Toxic Orb\n|upkeep\n|turn|6\n|\n|t:|1781453682\n|move|p2a: Zangoose|Close Combat|p1a: Dialga\n|-supereffective|p1a: Dialga\n|-damage|p1a: Dialga|0 fnt\n|-unboost|p2a: Zangoose|def|1\n|-unboost|p2a: Zangoose|spd|1\n|faint|p1a: Dialga\n|\n|-damage|p2a: Zangoose|247/263 tox|[from] psn\n|upkeep\n|inactive|wazzzhole has 120 seconds left.\n|\n|t:|1781453706\n|switch|p1a: Persian|Persian-Alola, L86, M|252/252\n|-damage|p1a: Persian|221/252|[from] Spikes\n|turn|7\n|inactive|imjustabanana has 120 seconds left.\n|\n|t:|1781453746\n|switch|p2a: Toucannon|Toucannon, L88, F|284/284\n|move|p1a: Persian|Dark Pulse|p2a: Toucannon\n|-damage|p2a: Toucannon|177/284\n|-damage|p1a: Persian|196/252|[from] item: Life Orb\n|\n|upkeep\n|turn|8\n|\n|t:|1781453757\n|move|p1a: Persian|Thunderbolt|p2a: Toucannon\n|-supereffective|p2a: Toucannon\n|-damage|p2a: Toucannon|24/284\n|-damage|p1a: Persian|171/252|[from] item: Life Orb\n|move|p2a: Toucannon|Boomburst|p1a: Persian\n|-damage|p1a: Persian|8/252\n|\n|upkeep\n|turn|9\n|inactive|imjustabanana has 120 seconds left.\n|\n|t:|1781453767\n|move|p1a: Persian|Burning Jealousy|p2a: Toucannon\n|-damage|p2a: Toucannon|0 fnt\n|faint|p2a: Toucannon\n|-damage|p1a: Persian|0 fnt|[from] item: Life Orb\n|faint|p1a: Persian\n|\n|upkeep\n|\n|t:|1781453776\n|switch|p1a: Breloom|Breloom, L83, F|235/235\n|switch|p2a: Zangoose|Zangoose, L85, M|247/263 tox\n|-damage|p1a: Breloom|206/235|[from] Spikes\n|turn|10\n|\n|t:|1781453783\n|-terastallize|p2a: Zangoose|Normal\n|move|p2a: Zangoose|Quick Attack|p1a: Breloom\n|-damage|p1a: Breloom|88/235\n|move|p1a: Breloom|Mach Punch|p2a: Zangoose\n|-supereffective|p2a: Zangoose\n|-damage|p2a: Zangoose|0 fnt\n|faint|p2a: Zangoose\n|-damage|p1a: Breloom|65/235|[from] item: Life Orb\n|\n|upkeep\n|-message|imjustabanana forfeited.\n|\n|win|wazzzhole\n|raw|wazzzhole's rating: 1698 &rarr; <strong>1719</strong><br />(+21 for winning)\n|raw|imjustabanana's rating: 1707 &rarr; <strong>1686</strong><br />(-21 for losing)\n|l|\u2606imjustabanana\n|player|p2|\n", "inputlog": ">version a8376a258c1d4662feba110a92103f3664a72141\n>start {\"formatid\":\"gen9randombattle\",\"seed\":\"sodium,126e9433e5da92ccc32b3396cf32f468\",\"rated\":\"Rated battle\"}\n>player p1 {\"name\":\"wazzzhole\",\"avatar\":\"266\",\"rating\":1698,\"seed\":\"sodium,77e740893fb035976b12ce6f9742e97b\"}\n>player p2 {\"name\":\"imjustabanana\",\"avatar\":\"giovanni\",\"rating\":1707,\"seed\":\"sodium,ea84ee76cfa6a11d543475525f30032b\"}\n>p1 move sunnyday\n>p2 move calmmind\n>p1 move weatherball terastallize\n>p2 move moonblast\n>p2 switch 6\n>p1 move weatherball\n>p2 move earthpower\n>p2 switch 4\n>p1 move weatherball\n>p2 move spikes\n>p2 switch 5\n>p1 switch 6\n>p2 move quickattack\n>p1 move stealthrock\n>p2 move closecombat\n>p1 switch 5\n>p1 move darkpulse\n>p2 switch 2\n>p1 move thunderbolt\n>p2 move boomburst\n>p1 move burningjealousy\n>p2 move roost\n>p1 switch 2\n>p2 switch 2\n>p1 move machpunch\n>p2 move quickattack terastallize\n>forcelose p2", "uploadtime": 1781453793, "views": 6, "formatid": "gen9randombattle", "rating": 1686, "private": 0, "password": null, "player_dets": [{"name": "wazzzhole", "avatar": "266", "rating": 1698, "seed": "sodium,77e740893fb035976b12ce6f9742e97b"}, {"name": "imjustabanana", "avatar": "giovanni", "rating": 1707, "seed": "sodium,ea84ee76cfa6a11d543475525f30032b"}], "teams_full": [{"Sunflora": {"name": "Sunflora", "species": "Sunflora", "speciesId": "sunflora", "gender": "M", "shiny": false, "level": 100, "moves": ["earthpower", "solarbeam", "weatherball", "sunnyday"], "ability": "Chlorophyll", "evs": {"hp": 85, "atk": 0, "def": 85, "spa": 85, "spd": 85, "spe": 85}, "ivs": {"hp": 31, "atk": 0, "def": 31, "spa": 31, "spd": 31, "spe": 31}, "item": "Life Orb", "teraType": "Fire", "role": "Setup Sweeper", "bvs": {"hp": 75, "atk": 75, "def": 55, "spa": 105, "spd": 85, "spe": 30}, "stats": {"hp": 312, "atk": 155, "def": 167, "spa": 267, "spd": 227, "spe": 117}, "types": ["Grass"]}, "Breloom": {"name": "Breloom", "species": "Breloom", "speciesId": "breloom", "gender": "F", "shiny": false, "level": 83, "moves": ["machpunch", "rocktomb", "bulletseed", "spore"], "ability": "Technician", "evs": {"hp": 85, "atk": 85, "def": 85, "spa": 85, "spd": 85, "spe": 85}, "ivs": {"hp": 31, "atk": 31, "def": 31, "spa": 31, "spd": 31, "spe": 31}, "item": "Life Orb", "teraType": "Rock", "role": "Fast Attacker", "bvs": {"hp": 60, "atk": 130, "def": 80, "spa": 60, "spd": 60, "spe": 70}, "stats": {"hp": 235, "atk": 263, "def": 180, "spa": 147, "spd": 147, "spe": 164}, "types": ["Grass", "Fighting"]}, "Registeel": {"name": "Registeel", "species": "Registeel", "speciesId": "registeel", "gender": "N", "shiny": false, "level": 81, "moves": ["ironhead", "rest", "irondefense", "bodypress"], "ability": "Clear Body", "evs": {"hp": 85, "atk": 85, "def": 85, "spa": 85, "spd": 85, "spe": 85}, "ivs": {"hp": 31, "atk": 31, "def": 31, "spa": 31, "spd": 31, "spe": 31}, "item": "Chesto Berry", "teraType": "Fighting", "role": "Bulky Setup", "bvs": {"hp": 80, "atk": 75, "def": 150, "spa": 75, "spd": 150, "spe": 50}, "stats": {"hp": 262, "atk": 168, "def": 290, "spa": 168, "spd": 290, "spe": 128}, "types": ["Steel"]}, "Haxorus": {"name": "Haxorus", "species": "Haxorus", "speciesId": "haxorus", "gender": "F", "shiny": false, "level": 77, "moves": ["outrage", "ironhead", "earthquake", "dragondance"], "ability": "Mold Breaker", "evs": {"hp": 85, "atk": 85, "def": 85, "spa": 85, "spd": 85, "spe": 85}, "ivs": {"hp": 31, "atk": 31, "def": 31, "spa": 31, "spd": 31, "spe": 31}, "item": "Lum Berry", "teraType": "Steel", "role": "Setup Sweeper", "bvs": {"hp": 76, "atk": 147, "def": 90, "spa": 60, "spd": 70, "spe": 97}, "stats": {"hp": 244, "atk": 271, "def": 183, "spa": 137, "spd": 152, "spe": 194}, "types": ["Dragon"]}, "Persian": {"name": "Persian", "species": "Persian-Alola", "speciesId": "persianalola", "gender": "M", "shiny": false, "level": 86, "moves": ["nastyplot", "burningjealousy", "darkpulse", "thunderbolt"], "ability": "Fur Coat", "evs": {"hp": 85, "atk": 0, "def": 85, "spa": 85, "spd": 85, "spe": 85}, "ivs": {"hp": 31, "atk": 0, "def": 31, "spa": 31, "spd": 31, "spe": 31}, "item": "Life Orb", "teraType": "Electric", "role": "Fast Bulky Setup", "bvs": {"hp": 65, "atk": 60, "def": 60, "spa": 75, "spd": 65, "spe": 115}, "stats": {"hp": 252, "atk": 108, "def": 152, "spa": 178, "spd": 161, "spe": 247}, "types": ["Dark"]}, "Dialga": {"name": "Dialga", "species": "Dialga", "speciesId": "dialga", "gender": "N", "shiny": false, "level": 73, "moves": ["stealthrock", "fireblast", "dracometeor", "heavyslam"], "ability": "Pressure", "evs": {"hp": 85, "atk": 85, "def": 85, "spa": 85, "spd": 85, "spe": 85}, "ivs": {"hp": 31, "atk": 31, "def": 31, "spa": 31, "spd": 31, "spe": 31}, "item": "Leftovers", "teraType": "Steel", "role": "Bulky Attacker", "bvs": {"hp": 100, "atk": 120, "def": 120, "spa": 150, "spd": 100, "spe": 90}, "stats": {"hp": 266, "atk": 218, "def": 218, "spa": 261, "spd": 188, "spe": 174}, "types": ["Steel", "Dragon"]}}, {"Iron Valiant": {"name": "Iron Valiant", "species": "Iron Valiant", "speciesId": "ironvaliant", "gender": "N", "shiny": false, "level": 78, "moves": ["calmmind", "psychic", "closecombat", "moonblast"], "ability": "Quark Drive", "evs": {"hp": 85, "atk": 85, "def": 85, "spa": 85, "spd": 85, "spe": 85}, "ivs": {"hp": 31, "atk": 31, "def": 31, "spa": 31, "spd": 31, "spe": 31}, "item": "Life Orb", "teraType": "Steel", "role": "Fast Attacker", "bvs": {"hp": 74, "atk": 130, "def": 90, "spa": 120, "spd": 60, "spe": 116}, "stats": {"hp": 244, "atk": 248, "def": 185, "spa": 232, "spd": 139, "spe": 226}, "types": ["Fairy", "Fighting"]}, "Toucannon": {"name": "Toucannon", "species": "Toucannon", "speciesId": "toucannon", "gender": "F", "shiny": false, "level": 88, "moves": ["roost", "boomburst", "bulletseed", "beakblast"], "ability": "Skill Link", "evs": {"hp": 85, "atk": 85, "def": 85, "spa": 85, "spd": 85, "spe": 85}, "ivs": {"hp": 31, "atk": 31, "def": 31, "spa": 31, "spd": 31, "spe": 31}, "item": "Heavy-Duty Boots", "teraType": "Steel", "role": "Bulky Support", "bvs": {"hp": 80, "atk": 120, "def": 75, "spa": 75, "spd": 75, "spe": 60}, "stats": {"hp": 284, "atk": 261, "def": 182, "spa": 182, "spd": 182, "spe": 156}, "types": ["Normal", "Flying"]}, "Hippowdon": {"name": "Hippowdon", "species": "Hippowdon", "speciesId": "hippowdon", "gender": "F", "shiny": false, "level": 82, "moves": ["stoneedge", "stealthrock", "earthquake", "slackoff"], "ability": "Sand Stream", "evs": {"hp": 85, "atk": 85, "def": 85, "spa": 85, "spd": 85, "spe": 85}, "ivs": {"hp": 31, "atk": 31, "def": 31, "spa": 31, "spd": 31, "spe": 31}, "item": "Leftovers", "teraType": "Dragon", "role": "Bulky Support", "bvs": {"hp": 108, "atk": 112, "def": 118, "spa": 68, "spd": 72, "spe": 47}, "stats": {"hp": 311, "atk": 231, "def": 241, "spa": 159, "spd": 165, "spe": 124}, "types": ["Ground"]}, "Klefki": {"name": "Klefki", "species": "Klefki", "speciesId": "klefki", "gender": "F", "shiny": false, "level": 84, "moves": ["thunderwave", "dazzlinggleam", "foulplay", "spikes"], "ability": "Prankster", "evs": {"hp": 85, "atk": 0, "def": 85, "spa": 85, "spd": 85, "spe": 85}, "ivs": {"hp": 31, "atk": 0, "def": 31, "spa": 31, "spd": 31, "spe": 31}, "item": "Leftovers", "teraType": "Flying", "role": "Bulky Attacker", "bvs": {"hp": 57, "atk": 80, "def": 91, "spa": 80, "spd": 87, "spe": 75}, "stats": {"hp": 233, "atk": 139, "def": 201, "spa": 183, "spd": 194, "spe": 174}, "types": ["Steel", "Fairy"]}, "Zangoose": {"name": "Zangoose", "species": "Zangoose", "speciesId": "zangoose", "gender": "M", "shiny": false, "level": 85, "moves": ["closecombat", "facade", "knockoff", "quickattack"], "ability": "Toxic Boost", "evs": {"hp": 85, "atk": 85, "def": 85, "spa": 85, "spd": 85, "spe": 85}, "ivs": {"hp": 31, "atk": 31, "def": 31, "spa": 31, "spd": 31, "spe": 31}, "item": "Toxic Orb", "teraType": "Normal", "role": "Fast Attacker", "bvs": {"hp": 73, "atk": 115, "def": 60, "spa": 60, "spd": 60, "spe": 90}, "stats": {"hp": 263, "atk": 244, "def": 151, "spa": 151, "spd": 151, "spe": 202}, "types": ["Normal"]}, "Venusaur": {"name": "Venusaur", "species": "Venusaur", "speciesId": "venusaur", "gender": "M", "shiny": false, "level": 84, "moves": ["sludgebomb", "knockoff", "synthesis", "earthpower"], "ability": "Chlorophyll", "evs": {"hp": 85, "atk": 85, "def": 85, "spa": 85, "spd": 85, "spe": 85}, "ivs": {"hp": 31, "atk": 31, "def": 31, "spa": 31, "spd": 31, "spe": 31}, "item": "Leftovers", "teraType": "Dark", "role": "Bulky Attacker", "bvs": {"hp": 80, "atk": 82, "def": 83, "spa": 100, "spd": 100, "spe": 80}, "stats": {"hp": 272, "atk": 186, "def": 188, "spa": 216, "spd": 216, "spe": 183}, "types": ["Grass", "Poison"]}}]}